[
    {
        "key": "group_5b8ca1be3f127",
        "title": "Recipe",
        "fields": [
            {
                "key": "field_5b8ca2164b145",
                "label": "Ingredients & Timing",
                "name": "ingredients",
                "type": "group",
                "instructions": "",
                "required": 0,
                "conditional_logic": 0,
                "wrapper": {
                    "width": "",
                    "class": "",
                    "id": ""
                },
                "layout": "block",
                "sub_fields": [
                    {
                        "key": "field_5b8ca2d57d239",
                        "label": "Timing",
                        "name": "timing",
                        "type": "group",
                        "instructions": "",
                        "required": 0,
                        "conditional_logic": 0,
                        "wrapper": {
                            "width": "",
                            "class": "",
                            "id": ""
                        },
                        "layout": "block",
                        "sub_fields": [
                            {
                                "key": "field_5b8ca2f67d23a",
                                "label": "Prep Time",
                                "name": "prep_time",
                                "type": "number",
                                "instructions": "",
                                "required": 0,
                                "conditional_logic": 0,
                                "wrapper": {
                                    "width": "50",
                                    "class": "",
                                    "id": ""
                                },
                                "default_value": "",
                                "placeholder": 5,
                                "prepend": "",
                                "append": "Minutes",
                                "min": 0,
                                "max": "",
                                "step": ""
                            },
                            {
                                "key": "field_5b8ca3857d23c",
                                "label": "Active Time",
                                "name": "active_time",
                                "type": "number",
                                "instructions": "",
                                "required": 0,
                                "conditional_logic": 0,
                                "wrapper": {
                                    "width": "50",
                                    "class": "",
                                    "id": ""
                                },
                                "default_value": "",
                                "placeholder": 20,
                                "prepend": "",
                                "append": "Minutes",
                                "min": 0,
                                "max": "",
                                "step": ""
                            }
                        ]
                    },
                    {
                        "key": "field_5b8ca2384b146",
                        "label": "Ingredients",
                        "name": "ingredients",
                        "type": "repeater",
                        "instructions": "",
                        "required": 0,
                        "conditional_logic": 0,
                        "wrapper": {
                            "width": "",
                            "class": "",
                            "id": ""
                        },
                        "collapsed": "field_5b8ca2704b147",
                        "min": 0,
                        "max": 0,
                        "layout": "block",
                        "button_label": "Add Ingredient",
                        "sub_fields": [
                            {
                                "key": "field_5b8ca29d4b148",
                                "label": "Measurement",
                                "name": "measurement",
                                "type": "text",
                                "instructions": "",
                                "required": 0,
                                "conditional_logic": 0,
                                "wrapper": {
                                    "width": "25",
                                    "class": "",
                                    "id": ""
                                },
                                "default_value": "",
                                "placeholder": "2 Cups",
                                "prepend": "",
                                "append": "",
                                "maxlength": ""
                            },
                            {
                                "key": "field_5b8ca2704b147",
                                "label": "Ingredient",
                                "name": "ingredient",
                                "type": "text",
                                "instructions": "",
                                "required": 0,
                                "conditional_logic": 0,
                                "wrapper": {
                                    "width": "75",
                                    "class": "",
                                    "id": ""
                                },
                                "default_value": "",
                                "placeholder": "Carrots",
                                "prepend": "",
                                "append": "",
                                "maxlength": ""
                            }
                        ]
                    }
                ]
            },
            {
                "key": "field_5b8ca44ae5cd9",
                "label": "Process",
                "name": "process",
                "type": "group",
                "instructions": "",
                "required": 0,
                "conditional_logic": 0,
                "wrapper": {
                    "width": "",
                    "class": "",
                    "id": ""
                },
                "layout": "block",
                "sub_fields": [
                    {
                        "key": "field_5b8ca45ae5cda",
                        "label": "Steps",
                        "name": "steps",
                        "type": "repeater",
                        "instructions": "",
                        "required": 0,
                        "conditional_logic": 0,
                        "wrapper": {
                            "width": "",
                            "class": "",
                            "id": ""
                        },
                        "collapsed": "field_5b8ca48ce5cdb",
                        "min": 0,
                        "max": 0,
                        "layout": "block",
                        "button_label": "Add Step",
                        "sub_fields": [
                            {
                                "key": "field_5b8ca48ce5cdb",
                                "label": "Step",
                                "name": "step",
                                "type": "wysiwyg",
                                "instructions": "",
                                "required": 0,
                                "conditional_logic": 0,
                                "wrapper": {
                                    "width": "",
                                    "class": "",
                                    "id": ""
                                },
                                "default_value": "",
                                "tabs": "all",
                                "toolbar": "full",
                                "media_upload": 1,
                                "delay": 0
                            }
                        ]
                    }
                ]
            }
        ],
        "location": [
            [
                {
                    "param": "post_type",
                    "operator": "==",
                    "value": "recipe"
                }
            ]
        ],
        "menu_order": 0,
        "position": "normal",
        "style": "default",
        "label_placement": "top",
        "instruction_placement": "label",
        "hide_on_screen": "",
        "active": 1,
        "description": ""
    }
]